LICENSE
README
TransmissionClient.py
setup.py
TransmissionClient.egg-info/PKG-INFO
TransmissionClient.egg-info/SOURCES.txt
TransmissionClient.egg-info/dependency_links.txt
TransmissionClient.egg-info/requires.txt
TransmissionClient.egg-info/top_level.txt
TransmissionClient.egg-info/zip-safe
test/README.html
test/README.rst
test/__init__.py
test/testTransmissionClient.py
test/data/bar_torrent.txt.torrent
test/data/foo_torrent.txt.torrent
test/data/test_torrent.torrent
