Metadata-Version: 1.0
Name: TransmissionClient
Version: 0.1
Summary: Python bindings for the Transmission BitTorrent Client
Home-page: http://code.google.com/p/py-transmission/
Author: Tom Lazar
Author-email: tom@tomster.org
License: MIT License
Keywords: bittorrent transmission
Platform: UNKNOWN
Classifier: Development Status :: 3 - Alpha
Classifier: Intended Audience :: Developers
Classifier: License :: OSI Approved :: MIT License
Classifier: Operating System :: OS Independent
Classifier: Programming Language :: Python
Classifier: Topic :: Communications :: File Sharing
